pdf_cli/__init__.py
pdf_cli/main.py
pdf_cli/utils.py
pdf_cli/version.py
pdf_cli/commands/__init__.py
pdf_cli/commands/decrypt.py
pdf_cli/commands/encrypt.py
pdf_cli/commands/extract.py
pdf_cli/commands/info.py
pdf_cli/commands/join.py
pdf_cli/commands/ocr.py
pdf_cli/commands/rotate.py
pdf_cli/commands/split.py
pdf_cli/commands/watermark.py
pdf_cli-1.0.dist-info/METADATA
pdf_cli-1.0.dist-info/WHEEL
pdf_cli-1.0.dist-info/entry_points.txt
pdf_cli-1.0.dist-info/licenses/LICENSE
pdf_cli-1.0.dist-info/RECORD
