Metadata-Version: 2.4
Name: pdf-cli
Version: 1.0
Summary: command line pdf tools
Project-URL: CI, https://github.com/saxix/pdfcli/actions
Project-URL: Homepage, https://github.com/saxix/pdfcli
Project-URL: Issues, https://github.com/saxix/pdfcli/issues
License: MIT License
License-File: LICENSE
Keywords: pdf
Classifier: Programming Language :: Python :: 3 :: Only
Classifier: Programming Language :: Python :: 3.9
Classifier: Programming Language :: Python :: 3.10
Classifier: Programming Language :: Python :: 3.11
Classifier: Programming Language :: Python :: 3.12
Classifier: Programming Language :: Python :: 3.13
Requires-Python: >=3.9
Requires-Dist: click
Requires-Dist: cloup>=3.0.7
Requires-Dist: cryptography>=3.1
Requires-Dist: pypdf
Requires-Dist: pytesseract>=0.3.13
